remarkable/__init__.py
remarkable/base/RemarkableOCR.py
remarkable/base/__init__.py
remarkable/base/core/RemarkableOCRResearch.py
remarkable/base/core/__init__.py
remarkable/base/core/lightweight_utilities/__init__.py
remarkable/base/core/lightweight_utilities/colors.py
remarkable/base/core/lightweight_utilities/utils.py
RemarkableOCR-2024.9.2.dist-info/LICENSE
RemarkableOCR-2024.9.2.dist-info/METADATA
RemarkableOCR-2024.9.2.dist-info/WHEEL
RemarkableOCR-2024.9.2.dist-info/top_level.txt
RemarkableOCR-2024.9.2.dist-info/RECORD
