Metadata-Version: 2.1
Name: RemarkableOCR
Version: 2024.9.2
Summary: RemarkableOCR is a simple ocr tool with improved data, analytics, and rendering tools.
Author-email: Starlight <david@starlight.ai>
Maintainer-email: Starlight <david@starlight.ai>
Project-URL: Homepage, https://github.com/markelwin/RemarkableOCR
Project-URL: Repository, https://github.com/markelwin/RemarkableOCR.git
Project-URL: Issues, https://github.com/markelwin/RemarkableOCR/issues
Keywords: remarkable,ocr,optical character recognition,machine learning,computer vision,books
Classifier: Development Status :: 4 - Beta
Classifier: Programming Language :: Python :: 3
Classifier: License :: OSI Approved :: GNU General Public License v3 (GPLv3)
Classifier: Operating System :: OS Independent
Requires-Python: >=3.8
License-File: LICENSE
Requires-Dist: pytesseract
Requires-Dist: Pillow
Requires-Dist: numpy
Requires-Dist: scikit-image
